[1,["36HsTaeNNJ8YSFSzEkgTfn"],0,[["sp.SkeletonData",["_name","_atlasText","textureNames","_skeletonJson","textures"],-1,3]],[[0,0,1,2,3,4,5]],[[0,"build_tavern","\nbuild_tavern.png\nsize: 756,214\nformat: RGBA8888\nfilter: Linear,Linear\nrepeat: none\n1\n  rotate: false\n  xy: 2, 6\n  size: 256, 206\n  orig: 292, 206\n  offset: 30, 0\n  index: -1\n1202029\n  rotate: true\n  xy: 650, 91\n  size: 121, 104\n  orig: 121, 104\n  offset: 0, 0\n  index: -1\n1202035\n  rotate: true\n  xy: 260, 13\n  size: 199, 195\n  orig: 199, 195\n  offset: 0, 0\n  index: -1\n1202128\n  rotate: false\n  xy: 457, 2\n  size: 106, 70\n  orig: 106, 70\n  offset: 0, 0\n  index: -1\n1202148\n  rotate: true\n  xy: 457, 74\n  size: 138, 93\n  orig: 138, 93\n  offset: 0, 0\n  index: -1\n2\n  rotate: true\n  xy: 650, 33\n  size: 56, 92\n  orig: 57, 93\n  offset: 0, 0\n  index: -1\n2s\n  rotate: true\n  xy: 616, 54\n  size: 33, 32\n  orig: 34, 33\n  offset: 0, 1\n  index: -1\n3\n  rotate: false\n  xy: 565, 3\n  size: 49, 84\n  orig: 49, 84\n  offset: 0, 0\n  index: -1\nL3\n  rotate: false\n  xy: 552, 89\n  size: 96, 123\n  orig: 96, 123\n  offset: 0, 0\n  index: -1\n",["build_tavern.png"],{"skeleton":{"hash":"emX4eCfnP9Bq1qGeMYwMNIuuG0U","spine":"3.8.99","x":-142.96,"y":-61.13,"width":302.16,"height":233.5,"images":"./images/","audio":"/Volumes/Macintosh HD -数据/Users/tk/_项目资源/吕益纯/601_篝火少年团/场景/场景动画/ani/build_tavern"},"bones":[{"name":"root"},{"name":"bone","parent":"root","scaleX":0.5,"scaleY":0.5},{"name":"1","parent":"bone"},{"name":"3","parent":"1","x":-151.57,"y":266.74},{"name":"L3","parent":"bone","x":-45.92,"y":-35.42,"scaleX":0.6,"scaleY":0.6},{"name":"a1","parent":"root","x":-38.08,"y":29.95,"scaleX":0.5,"scaleY":0.5},{"name":"a2","parent":"root","x":91.16,"y":35.85,"scaleX":0.35,"scaleY":0.35},{"name":"a3","parent":"root","x":49.17,"y":-23.84,"scaleX":-0.5,"scaleY":0.5},{"name":"a4","parent":"root","x":37.36,"y":62.09,"scaleX":-0.5,"scaleY":0.5}],"slots":[{"name":"1202148","bone":"a4","color":"ffffff00","attachment":"1202148"},{"name":"1202029","bone":"a1","color":"ffffff00","attachment":"1202029"},{"name":"1202035","bone":"a2","color":"ffffff00","attachment":"1202035"},{"name":"1202128","bone":"a3","color":"ffffff00","attachment":"1202128"},{"name":"2","bone":"1","attachment":"2"},{"name":"3","bone":"3","attachment":"3"},{"name":"2s","bone":"1","attachment":"2s"},{"name":"1","bone":"1","attachment":"1"},{"name":"L3","bone":"L3","color":"ffffff00","attachment":"L3"}],"skins":[{"name":"default","attachments":{"1":{"1":{"x":5.58,"y":83.24,"width":583,"height":411}},"2":{"2":{"x":-132.92,"y":252.24,"width":114,"height":185}},"3":{"3":{"x":-9.85,"y":-57.5,"width":97,"height":167}},"1202029":{"1202029":{"x":5.9,"y":29.52,"width":242,"height":208}},"1202035":{"1202035":{"x":-4.59,"y":64.29,"width":398,"height":390}},"1202128":{"1202128":{"x":-0.66,"y":1.31,"width":212,"height":140}},"1202148":{"1202148":{"x":9.84,"y":12.46,"width":276,"height":186}},"2s":{"2s":{"x":-155.92,"y":284.24,"width":68,"height":65}},"L3":{"L3":{"x":4.08,"y":39.37,"width":192,"height":246}}}}],"animations":{"1":{"slots":{"1":{"color":[{"color":"ffffff00"}]},"2":{"color":[{"color":"ffffff00"}]},"3":{"color":[{"color":"ffffff00"}]},"1202029":{"color":[{"color":"ffffffff"}]},"1202035":{"color":[{"color":"ffffffff"}]},"1202128":{"color":[{"color":"ffffffff"}]},"1202148":{"color":[{"color":"ffffffff"}]},"2s":{"color":[{"color":"ffffff00"}]},"L3":{"color":[{"color":"ffffffff"}]}},"bones":{"L3":{"translate":[{"curve":0.25,"c3":0.75},{"time":0.0667,"x":1.31}]}}},"2":{"slots":{"1":{"color":[{"color":"ffffff00","curve":"stepped"},{"time":1.6667,"color":"ffffff00","curve":0.25,"c3":0.75},{"time":1.8333,"color":"ffffffff"}]},"2":{"color":[{"color":"ffffff00","curve":"stepped"},{"time":1.6667,"color":"ffffff00","curve":0.25,"c3":0.75},{"time":1.8333,"color":"ffffffff"}]},"3":{"color":[{"color":"ffffff00","curve":"stepped"},{"time":1.6667,"color":"ffffff00","curve":0.25,"c3":0.75},{"time":1.8333,"color":"ffffffff"}]},"1202029":{"color":[{"color":"ffffffff","curve":"stepped"},{"time":0.3,"color":"ffffffff","curve":0.25,"c3":0.75},{"time":0.4667,"color":"ffffff00"}]},"1202035":{"color":[{"color":"ffffffff","curve":"stepped"},{"time":0.9,"color":"ffffffff","curve":0.25,"c3":0.75},{"time":1.0667,"color":"ffffff00"}]},"1202128":{"color":[{"color":"ffffffff","curve":"stepped"},{"time":0.5333,"color":"ffffffff","curve":0.25,"c3":0.75},{"time":0.7,"color":"ffffff00"}]},"1202148":{"color":[{"color":"ffffffff","curve":"stepped"},{"time":0.6333,"color":"ffffffff","curve":0.25,"c3":0.75},{"time":0.8,"color":"ffffff00"}]},"2s":{"color":[{"color":"ffffff00","curve":"stepped"},{"time":1.6667,"color":"ffffff00","curve":0.25,"c3":0.75},{"time":1.8333,"color":"ffffffff"}]},"L3":{"color":[{"color":"ffffffff"}]}},"bones":{"1":{"translate":[{}],"scale":[{"x":0,"y":0,"curve":"stepped"},{"time":1.6667,"x":0,"y":0,"curve":0,"c2":0.85,"c3":0.75},{"time":1.9,"x":1.2,"y":1.2,"curve":0.25,"c3":0.75},{"time":2}]},"3":{"shear":[{"y":-17.33,"curve":"stepped"},{"time":1.8333,"y":-17.33,"curve":0.25,"c3":0.625,"c4":0.5},{"time":2.1667,"y":10.5,"curve":0.375,"c2":0.5,"c3":0.75},{"time":2.5}]},"L3":{"translate":[{"curve":"stepped"},{"time":1,"curve":0.25,"c3":0.75},{"time":1.1667,"y":73,"curve":"stepped"},{"time":1.3333,"y":73,"curve":0.25,"c3":0.75},{"time":1.5}],"scale":[{"curve":"stepped"},{"time":1,"curve":0.25,"c3":0.75},{"time":1.1667,"x":1.25,"y":1.25,"curve":0.25,"c3":0.75},{"time":1.3333,"x":1.5,"y":1.5,"curve":0.25,"c3":0.75},{"time":1.5,"x":0,"y":0}]},"a3":{"rotate":[{"time":0.3667,"curve":0.25,"c3":0.75},{"time":0.7,"angle":22.8}],"translate":[{"curve":"stepped"},{"time":0.3667,"curve":0.25,"c3":0.75},{"time":0.7,"y":85.28}]},"a4":{"rotate":[{"time":0.4667,"curve":0.25,"c3":0.75},{"time":0.8,"angle":-31.7}],"translate":[{"curve":"stepped"},{"time":0.4667,"curve":0.25,"c3":0.75},{"time":0.8,"y":85.28}]},"a1":{"rotate":[{"time":0.1333,"curve":0.25,"c3":0.75},{"time":0.4667,"angle":10.08}],"translate":[{"curve":"stepped"},{"time":0.1333,"curve":0.25,"c3":0.75},{"time":0.4667,"y":85.28}]},"a2":{"rotate":[{"time":0.7333,"curve":0.25,"c3":0.75},{"time":1.0667,"angle":10.08}],"translate":[{"curve":"stepped"},{"time":0.7333,"curve":0.25,"c3":0.75},{"time":1.0667,"y":85.28}]}},"drawOrder":[{"time":0.3667,"offsets":[{"slot":"1202128","offset":5}]}]},"3":{"bones":{"3":{"shear":[{},{"time":0.4,"y":-5.69},{"time":0.8333},{"time":1.2333,"y":5.37},{"time":1.6667}]}}}}},[0]]],0,0,[0],[-1],[0]]